<annotation>
	<folder>failed</folder>
	<filename>1_failed_239.jpg</filename>
	<path>C:\Users\hartw\GitHub\3DPrintCheck\failed\1_failed_239.jpg</path>
	<source>
		<database>Unknown</database>
	</source>
	<size>
		<width>256</width>
		<height>197</height>
		<depth>3</depth>
	</size>
	<segmented>0</segmented>
	<object>
		<name>fail</name>
		<pose>Unspecified</pose>
		<truncated>0</truncated>
		<difficult>0</difficult>
		<bndbox>
			<xmin>151</xmin>
			<ymin>64</ymin>
			<xmax>187</xmax>
			<ymax>94</ymax>
		</bndbox>
	</object>
	<object>
		<name>fail</name>
		<pose>Unspecified</pose>
		<truncated>0</truncated>
		<difficult>0</difficult>
		<bndbox>
			<xmin>26</xmin>
			<ymin>132</ymin>
			<xmax>129</xmax>
			<ymax>192</ymax>
		</bndbox>
	</object>
</annotation>
