<annotation>
	<folder>failed</folder>
	<filename>1_failed_92.jpg</filename>
	<path>C:\Users\hartw\GitHub\3DPrintCheck\failed\1_failed_92.jpg</path>
	<source>
		<database>Unknown</database>
	</source>
	<size>
		<width>313</width>
		<height>161</height>
		<depth>3</depth>
	</size>
	<segmented>0</segmented>
	<object>
		<name>fail</name>
		<pose>Unspecified</pose>
		<truncated>0</truncated>
		<difficult>0</difficult>
		<bndbox>
			<xmin>65</xmin>
			<ymin>65</ymin>
			<xmax>153</xmax>
			<ymax>149</ymax>
		</bndbox>
	</object>
	<object>
		<name>fail</name>
		<pose>Unspecified</pose>
		<truncated>0</truncated>
		<difficult>0</difficult>
		<bndbox>
			<xmin>150</xmin>
			<ymin>84</ymin>
			<xmax>263</xmax>
			<ymax>147</ymax>
		</bndbox>
	</object>
</annotation>
